{
  "headache": {
    "id": "S1",
    "name": "Headache",
    "description": "Pain in the head or upper neck"
  },
  "fever": {
    "id": "S2",
    "name": "Fever",
    "description": "Elevated body temperature above normal range"
  },
  "cough": {
    "id": "S3",
    "name": "Cough",
    "description": "Sudden expulsion of air from the lungs"
  },
  "fatigue": {
    "id": "S4",
    "name": "Fatigue",
    "description": "Extreme tiredness or exhaustion"
  },
  "nausea": {
    "id": "S5",
    "name": "Nausea",
    "description": "Sensation of unease in the stomach with an urge to vomit"
  },
  "shortness_of_breath": {
    "id": "S6",
    "name": "Shortness of Breath",
    "description": "Difficulty breathing or dyspnea"
  },
  "sore_throat": {
    "id": "S7",
    "name": "Sore Throat",
    "description": "Pain or irritation in the throat"
  },
  "dizziness": {
    "id": "S8",
    "name": "Dizziness",
    "description": "Feeling faint, woozy, or unsteady"
  }
}